[
  {
    "downloaded_video": false,
    "created": 1379998102029,
    "id": "STOP_RELYING_ON_THIS",
    "title": "<fill this in>",
    "url": "http://www.amazon.com/WWE-History-World-Heavyweight-Championship/dp/B002NXSRNY/ref=sr_1_37?s=movies-tv&ie=UTF8&qid=1379997827&sr=1-37&keywords=wwe",
    "parentId": "221026",
    "ordinal": 1379998102029
  },
  {
    "downloaded_video": false,
    "created": 1379998511860,
    "id": "STOP_RELYING_ON_THIS",
    "title": "<fill this in>",
    "url": "http://www.amazon.com/Ric-Flair-Four-Horsemen/dp/B000LC3III/ref=sr_1_101?s=movies-tv&ie=UTF8&qid=1379998285&sr=1-101&keywords=wwe",
    "parentId": "221026",
    "ordinal": 1379998511860
  },
  {
    "downloaded_video": false,
    "created": 1379998535939,
    "id": "STOP_RELYING_ON_THIS",
    "title": "<fill this in>",
    "url": "http://www.amazon.com/WWE-Jeff-Hardy-Life-Rules/dp/B002NXSROS/ref=sr_1_114?s=movies-tv&ie=UTF8&qid=1379998322&sr=1-114&keywords=wwe",
    "parentId": "221026",
    "ordinal": 1379998535939
  },
  {
    "downloaded_video": false,
    "created": 1379998535939,
    "id": "STOP_RELYING_ON_THIS",
    "title": "<fill this in>",
    "url": "http://www.amazon.com/WWE-Jeff-Hardy-Life-Rules/dp/B002NXSROS/ref=sr_1_114?s=movies-tv&ie=UTF8&qid=1379998322&sr=1-114&keywords=wwe",
    "parentId": "221026",
    "ordinal": 1379998535939
  },
  {
    "downloaded_video": false,
    "created": 1379999140009,
    "id": "STOP_RELYING_ON_THIS",
    "title": "<fill this in>",
    "url": "http://www.amazon.com/Rise-Fall-ECW-Pit-Bulls/dp/B0001Y4LZU/ref=sr_1_163?s=movies-tv&ie=UTF8&qid=1379998817&sr=1-163&keywords=wwe",
    "parentId": "221026",
    "ordinal": 1379999140009
  },
  {
    "downloaded_video": false,
    "created": 1379999340441,
    "id": "STOP_RELYING_ON_THIS",
    "title": "<fill this in>",
    "url": "http://www.amazon.com/Best-WWE-Confidential-Vol/dp/B00007M5K7/ref=sr_1_339?s=movies-tv&ie=UTF8&qid=1379999021&sr=1-339&keywords=wwe",
    "parentId": "221026",
    "ordinal": 1379999340441
  },
  {
    "downloaded_video": false,
    "created": 1379999380912,
    "id": "STOP_RELYING_ON_THIS",
    "title": "<fill this in>",
    "url": "http://www.amazon.com/WWE-Knocks-Chris-Benoit-Story/dp/B00028G6TO/ref=sr_1_347?s=movies-tv&ie=UTF8&qid=1379999021&sr=1-347&keywords=wwe",
    "parentId": "221026",
    "ordinal": 1379999380912
  },
  {
    "downloaded_video": false,
    "created": 1379999388384,
    "id": "STOP_RELYING_ON_THIS",
    "title": "<fill this in>",
    "url": "http://www.amazon.com/WWE-John-Morrison-Rock-Star/dp/B002WNUVNE/ref=sr_1_348?s=movies-tv&ie=UTF8&qid=1379999021&sr=1-348&keywords=wwe",
    "parentId": "221026",
    "ordinal": 1379999388384
  },
  {
    "downloaded_video": false,
    "created": 1379999420555,
    "id": "STOP_RELYING_ON_THIS",
    "title": "<fill this in>",
    "url": "http://www.amazon.com/WWE-Rey-Mysterio-Oscar-Gutiérrez/dp/B00008HCA4/ref=sr_1_363?s=movies-tv&ie=UTF8&qid=1379999056&sr=1-363&keywords=wwe",
    "parentId": "221026",
    "ordinal": 1379999420555
  },
  {
    "downloaded_video": false,
    "created": 1379999940126,
    "id": "STOP_RELYING_ON_THIS",
    "title": "<fill this in>",
    "url": "http://www.amazon.com/WWE-Unauthorized-Artist-Not-Provided/dp/B000MRNWHY/ref=sr_1_408?s=movies-tv&ie=UTF8&qid=1379999579&sr=1-408&keywords=wwe",
    "parentId": "221026",
    "ordinal": 1379999940126
  },
  {
    "downloaded_video": false,
    "created": 1380000200487,
    "id": "STOP_RELYING_ON_THIS",
    "title": "<fill this in>",
    "url": "http://www.amazon.com/Unreal-Story-Pro-Wrestling/dp/B00003OSSP/ref=sr_1_520?s=movies-tv&ie=UTF8&qid=1379999731&sr=1-520&keywords=wwe",
    "parentId": "221026",
    "ordinal": 1380000200487
  },
  {
    "downloaded_video": false,
    "created": 1380000626912,
    "id": "STOP_RELYING_ON_THIS",
    "title": "<fill this in>",
    "url": "http://www.amazon.com/WWE-UNAUTHORIZED/dp/B000JXYJNW/ref=sr_1_541?s=movies-tv&ie=UTF8&qid=1379999751&sr=1-541&keywords=wwe",
    "parentId": "221026",
    "ordinal": 1380000626912
  },
  {
    "downloaded_video": false,
    "created": 1399091610775,
    "id": "STOP_RELYING_ON_THIS",
    "title": "<fill this in>",
    "url": "http://www.amazon.com/Best-Raw-After-Show-Blu-ray/dp/B00HRYH6DG",
    "parentId": "221026",
    "ordinal": 1399091610775
  },
  {
    "downloaded_video": false,
    "created": 1401162927993,
    "id": "STOP_RELYING_ON_THIS",
    "title": "<fill this in>",
    "url": "http://www.amazon.com/Greatest-Wrestling-Factions-Blu-ray-Horsemen/dp/B00HRUQ7UI/ref=sr_1_1?ie=UTF8&qid=1401162902&sr=8-1&keywords=greatest wrestling factions",
    "parentId": "221026",
    "ordinal": 1401162927993
  },
  {
    "downloaded_video": false,
    "created": 1401162927993,
    "id": "STOP_RELYING_ON_THIS",
    "title": "<fill this in>",
    "url": "http://www.amazon.com/Greatest-Wrestling-Factions-Blu-ray-Horsemen/dp/B00HRUQ7UI/ref=sr_1_1?ie=UTF8&qid=1401162902&sr=8-1&keywords=greatest wrestling factions",
    "parentId": "221026",
    "ordinal": 1401162927993
  },
  {
    "downloaded_video": false,
    "created": 1407020987325,
    "id": "STOP_RELYING_ON_THIS",
    "title": "<fill this in>",
    "url": "http://www.amazon.com/Management-Information-Systems-11th-Edition/dp/013607846X/ref=wl_it_dp_o_pC_nS_nC?ie=UTF8&amp;colid=1CZT5M13VEWRE&amp;coliid=IOOPYN6LC6DH2",
    "parentId": "221026",
    "ordinal": 1407020987325
  },
  {
    "downloaded_video": false,
    "created": 1407023491553,
    "id": "STOP_RELYING_ON_THIS",
    "title": "<fill this in>",
    "url": "http://www.dailymotion.com/video/x1cph7z_wwe-rise-and-fall-of-wcw-disc-1-part-1_sport",
    "parentId": "221026",
    "ordinal": 1407023491553
  },
  {
    "downloaded_video": false,
    "created": 1407023493523,
    "id": "STOP_RELYING_ON_THIS",
    "title": "<fill this in>",
    "url": "http://www.dailymotion.com/video/x1cpto5_wwe-rise-and-fall-of-wcw-disc-1-part-2_sport",
    "parentId": "221026",
    "ordinal": 1407023493523
  },
  {
    "downloaded_video": false,
    "created": 1407023497320,
    "id": "STOP_RELYING_ON_THIS",
    "title": "<fill this in>",
    "url": "http://www.dailymotion.com/video/x11702o_trish-stratus-wwe-confidential-photoshoot_sport",
    "parentId": "221026",
    "ordinal": 1407023497320
  },
  {
    "downloaded_video": false,
    "created": 1407023500360,
    "id": "STOP_RELYING_ON_THIS",
    "title": "<fill this in>",
    "url": "http://www.dailymotion.com/video/x17083c_wwe-confidential-september-13-2003_sport",
    "parentId": "221026",
    "ordinal": 1407023500360
  },
  {
    "downloaded_video": false,
    "created": 1407023502470,
    "id": "STOP_RELYING_ON_THIS",
    "title": "<fill this in>",
    "url": "http://www.dailymotion.com/video/x1anby5_sable-interview-outside-the-ropes-wwe-confidential_people",
    "parentId": "221026",
    "ordinal": 1407023502470
  },
  {
    "downloaded_video": false,
    "created": 1407023728907,
    "id": "STOP_RELYING_ON_THIS",
    "title": "<fill this in>",
    "url": "http://www.dailymotion.com/video/x17083l_wwe-confidential-september-20-2003_sport",
    "parentId": "221026",
    "ordinal": 1407023728907
  },
  {
    "downloaded_video": false,
    "created": 1407023730421,
    "id": "STOP_RELYING_ON_THIS",
    "title": "<fill this in>",
    "url": "http://www.dailymotion.com/video/x17082v_wwe-confidential-september-6-2003_sport",
    "parentId": "221026",
    "ordinal": 1407023730421
  },
  {
    "downloaded_video": false,
    "created": 1407023734797,
    "id": "STOP_RELYING_ON_THIS",
    "title": "<fill this in>",
    "url": "http://www.dailymotion.com/video/x44kcz_wwe-confidential-stone-cold-steve-a_sport",
    "parentId": "221026",
    "ordinal": 1407023734797
  },
  {
    "downloaded_video": false,
    "created": 1407023738332,
    "id": "STOP_RELYING_ON_THIS",
    "title": "<fill this in>",
    "url": "http://www.dailymotion.com/video/x6lpdw_wwe-confidential-british-bulldog-da_sport",
    "parentId": "221026",
    "ordinal": 1407023738332
  },
  {
    "downloaded_video": false,
    "created": 1407023759103,
    "id": "STOP_RELYING_ON_THIS",
    "title": "<fill this in>",
    "url": "http://www.dailymotion.com/video/x17083c_wwe-confidential-september-13-2003_sport",
    "parentId": "221026",
    "ordinal": 1407023759103
  },
  {
    "downloaded_video": false,
    "created": 1425959815470,
    "id": "STOP_RELYING_ON_THIS",
    "title": "<fill this in>",
    "url": "http://www.amazon.com/gp/product/B00QUKZQTE/ref=pd_lpo_sbs_dp_ss_1?pf_rd_p=1944687662&pf_rd_s=lpo-top-stripe-1&pf_rd_t=201&pf_rd_i=B00QUJRZJ4&pf_rd_m=ATVPDKIKX0DER&pf_rd_r=0AJDG3A5J142HYYVM8K7",
    "parentId": "221026",
    "ordinal": 1425959815470
  },
  {
    "downloaded_video": false,
    "created": 1431811614453,
    "id": "STOP_RELYING_ON_THIS",
    "title": "<fill this in>",
    "url": "http://www.amazon.com/gp/product/B00UA15CCK?ie=UTF8&force-full-site=1&ref_=navm_ftr_fullsite",
    "parentId": "221026",
    "ordinal": 1431811614453
  },
  {
    "downloaded_video": false,
    "created": 1431811627194,
    "id": "STOP_RELYING_ON_THIS",
    "title": "<fill this in>",
    "url": "http://www.amazon.com/gp/product/B00W5IYR86?ie=UTF8&force-full-site=1&ref_=navm_ftr_fullsite",
    "parentId": "221026",
    "ordinal": 1431811627194
  },
  {
    "downloaded_video": false,
    "created": 1432441710056,
    "id": "STOP_RELYING_ON_THIS",
    "title": "<fill this in>",
    "url": "http://www.amazon.com/Are-All-Men-Pedophiles-Uncensored/dp/B00BCO00Y4/",
    "parentId": "221026",
    "ordinal": 1432441710056
  },
  {
    "downloaded_video": false,
    "created": 1432441710056,
    "id": "STOP_RELYING_ON_THIS",
    "title": "<fill this in>",
    "url": "http://www.amazon.com/Are-All-Men-Pedophiles-Uncensored/dp/B00BCO00Y4/",
    "parentId": "221026",
    "ordinal": 1432441710056
  },
  {
    "downloaded_video": false,
    "created": 1432747507405,
    "id": "STOP_RELYING_ON_THIS",
    "title": "<fill this in>",
    "url": "http://www.amazon.com/THE-ADVENTURE-ENGLISH-Adventure-English/dp/B001O7R75E",
    "parentId": "221026",
    "ordinal": 1432747507405
  },
  {
    "downloaded_video": false,
    "created": 1434649856804,
    "id": "STOP_RELYING_ON_THIS",
    "title": "<fill this in>",
    "url": "http://www.amazon.co.uk/dp/B00OBN4274/ref=pd_luc_rh_mrairec_02_02_t_img_lh?_encoding=UTF8&psc=1",
    "parentId": "221026",
    "ordinal": 1434649856804
  },
  {
    "downloaded_video": false,
    "created": 1434649874831,
    "id": "STOP_RELYING_ON_THIS",
    "title": "<fill this in>",
    "url": "http://www.amazon.co.uk/Gascoigne-DVD-Paul/dp/B00U2F8GLI/ref=pd_cp_74_3",
    "parentId": "221026",
    "ordinal": 1434649874831
  },
  {
    "downloaded_video": false,
    "created": 1434649888331,
    "id": "STOP_RELYING_ON_THIS",
    "title": "<fill this in>",
    "url": "http://www.amazon.co.uk/Once-More-For-Bobby-DVD/dp/B00U2HNW6U/ref=pd_sim_74_2?ie=UTF8&refRID=00F1QW8EBQPN5P10GWW7",
    "parentId": "221026",
    "ordinal": 1434649888331
  },
  {
    "downloaded_video": false,
    "created": 1434649901906,
    "id": "STOP_RELYING_ON_THIS",
    "title": "<fill this in>",
    "url": "http://www.amazon.co.uk/Sir-Bobby-Robson-Knight-Remember/dp/B002YD5R2C/ref=pd_sim_sbs_74_6?ie=UTF8&refRID=0TK9CP8R2126MJDMSKXV",
    "parentId": "221026",
    "ordinal": 1434649901906
  },
  {
    "downloaded_video": false,
    "created": 1434649913990,
    "id": "STOP_RELYING_ON_THIS",
    "title": "<fill this in>",
    "url": "http://www.amazon.co.uk/Just-Call-Me-Bobby-DVD/dp/B0000AISIG/ref=pd_sim_74_2?ie=UTF8&refRID=0SW3C18PKPBNB68Y0V6E",
    "parentId": "221026",
    "ordinal": 1434649913990
  },
  {
    "downloaded_video": false,
    "created": 1434649926906,
    "id": "STOP_RELYING_ON_THIS",
    "title": "<fill this in>",
    "url": "http://www.amazon.co.uk/Clough-The-Brian-Story-DVD/dp/B001U3ZUKG/ref=pd_sim_74_2?ie=UTF8&refRID=1E33BBMQV2GDK3NCSBGG",
    "parentId": "221026",
    "ordinal": 1434649926906
  },
  {
    "downloaded_video": false,
    "created": 1434649946533,
    "id": "STOP_RELYING_ON_THIS",
    "title": "<fill this in>",
    "url": "http://www.amazon.co.uk/Brian-Clough-His-Own-Words/dp/B00266WWSY/ref=pd_sim_74_1?ie=UTF8&refRID=178BW0GAVTXMG6NJFBDB",
    "parentId": "221026",
    "ordinal": 1434649946533
  },
  {
    "downloaded_video": false,
    "created": 1436672578385,
    "id": "STOP_RELYING_ON_THIS",
    "title": "<fill this in>",
    "url": "http://www.amazon.com/Randy-Orton-Evolution-Predator-Blu-ray/dp/B0055SJYMW/ref=sr_1_4?ie=UTF8&qid=1436672423&sr=8-4&keywords=rey mysterio documentary",
    "parentId": "221026",
    "ordinal": 1436672578385
  },
  {
    "downloaded_video": false,
    "created": 1436672579897,
    "id": "STOP_RELYING_ON_THIS",
    "title": "<fill this in>",
    "url": "http://www.amazon.com/WWE-Greatest-Superstars-Century-Blu-ray/dp/B004W48KH0/ref=sr_1_3?ie=UTF8&qid=1436672423&sr=8-3&keywords=rey mysterio documentary",
    "parentId": "221026",
    "ordinal": 1436672579897
  },
  {
    "downloaded_video": false,
    "created": 1439507582593,
    "id": "STOP_RELYING_ON_THIS",
    "title": "<fill this in>",
    "url": "http://www.amazon.co.uk/Night-Turin-Blu-ray-James-Erskine/dp/B003ATD7LW/ref=sr_1_3?ie=UTF8&qid=1439507534&sr=8-3&keywords=one night in turin",
    "parentId": "221026",
    "ordinal": 1439507582593
  },
  {
    "downloaded_video": false,
    "created": 1439507582593,
    "id": "STOP_RELYING_ON_THIS",
    "title": "<fill this in>",
    "url": "http://www.amazon.co.uk/Night-Turin-Blu-ray-James-Erskine/dp/B003ATD7LW/ref=sr_1_3?ie=UTF8&qid=1439507534&sr=8-3&keywords=one night in turin",
    "parentId": "221026",
    "ordinal": 1439507582593
  },
  {
    "downloaded_video": false,
    "created": 1439523621505,
    "id": "STOP_RELYING_ON_THIS",
    "title": "<fill this in>",
    "url": "http://www.amazon.com/Daniel-Bryan-Just-Say-Blu-ray/dp/B00UA0TYWK/ref=pd_sim_74_5?ie=UTF8&refRID=19PKX5Z9BP7EYTQAN03Q",
    "parentId": "221026",
    "ordinal": 1439523621505
  }
]