[
  {
    "downloaded_video": false,
    "created": 1383449487143,
    "id": "STOP_RELYING_ON_THIS",
    "title": "<fill this in>",
    "url": "http://www.amazon.com/History-World-Two-Hours-Blu-ray/dp/B006QVRW0S/ref=sr_1_3?ie=UTF8&qid=1383447350&sr=8-3&keywords=history of the world in 2 hours",
    "parentId": "230279",
    "ordinal": 1383449487143
  },
  {
    "downloaded_video": false,
    "created": 1418691917114,
    "id": "STOP_RELYING_ON_THIS",
    "title": "<fill this in>",
    "url": "http://www.amazon.com/gp/product/B000U1ZV4O/ref=oh_aui_detailpage_o05_s00?ie=UTF8&psc=1",
    "parentId": "230279",
    "ordinal": 1418691917114
  },
  {
    "downloaded_video": false,
    "created": 1418694235990,
    "id": "STOP_RELYING_ON_THIS",
    "title": "<fill this in>",
    "url": "http://www.amazon.com/gp/product/B00005JLR8/ref=oh_aui_detailpage_o03_s00?ie=UTF8&psc=1",
    "parentId": "230279",
    "ordinal": 1418694235990
  }
]