[
  {
    "downloaded_video": false,
    "created": 1384810163558,
    "id": "STOP_RELYING_ON_THIS",
    "title": "<fill this in>",
    "url": "http://www.amazon.com/Esars-Comic-Dictionary-Evan-Esar/dp/1162787031/ref=tmm_pap_title_0?_encoding=UTF8&sr=&qid=",
    "parentId": "239427",
    "ordinal": 1384810163558
  },
  {
    "downloaded_video": false,
    "created": 1390957610325,
    "id": "STOP_RELYING_ON_THIS",
    "title": "<fill this in>",
    "url": "http://www.amazon.com/Insults-Every-Should-Pocket-Companions/dp/1594745242/ref=pd_sim_b_6",
    "parentId": "239427",
    "ordinal": 1390957610325
  },
  {
    "downloaded_video": false,
    "created": 1426788219483,
    "id": "STOP_RELYING_ON_THIS",
    "title": "<fill this in>",
    "url": "http://www.amazon.com/Book-cking-Hilarious-Internet-Memes/dp/147835447X/ref=sr_1_5?s=books&ie=UTF8&qid=1426717293&sr=1-5&keywords=memes",
    "parentId": "239427",
    "ordinal": 1426788219483
  },
  {
    "downloaded_video": false,
    "created": 1427143500223,
    "id": "STOP_RELYING_ON_THIS",
    "title": "<fill this in>",
    "url": "http://www.amazon.com/Grumpy-Cat-A-Book/dp/1452126577",
    "parentId": "239427",
    "ordinal": 1427143500223
  },
  {
    "downloaded_video": false,
    "created": 1448679012856,
    "id": "STOP_RELYING_ON_THIS",
    "title": "<fill this in>",
    "url": "http://www.amazon.com/Henny-Youngmans-500-All-Time-Greatest/dp/1558174842",
    "parentId": "239427",
    "ordinal": 1448679012856
  },
  {
    "downloaded_video": false,
    "created": 1460408981168,
    "id": "STOP_RELYING_ON_THIS",
    "title": "<fill this in>",
    "url": "http://www.amazon.com/Awesome-Jokes-Liners-Pants-Laughter/dp/1481148710/ref=sr_1_1?ie=UTF8&qid=1355162599&sr=8-1&keywords=250 awesome jokes and one",
    "parentId": "239427",
    "ordinal": 1460408981168
  }
]